knitty_gritty-0.0.2.dist-info/DESCRIPTION.rst
knitty_gritty-0.0.2.dist-info/entry_points.txt
knitty_gritty-0.0.2.dist-info/METADATA
knitty_gritty-0.0.2.dist-info/metadata.json
knitty_gritty-0.0.2.dist-info/RECORD
knitty_gritty-0.0.2.dist-info/top_level.txt
knitty_gritty-0.0.2.dist-info/WHEEL
knittygritty/__init__.py
knittygritty/bitmap.py
knittygritty/fdcemu.py
knittygritty/kh940.py
knittygritty/main.py
knittygritty/util.py
