Metadata-Version: 2.0
Name: knitty-gritty
Version: 0.0.2
Summary: A tool for managing knitting machine patterns
Home-page: https://github.com/mhallin/knitty-gritty
Author: Magnus Hallin
Author-email: mhallin@gmail.com
License: BSD
Platform: UNKNOWN
Requires-Dist: click (>=2.4,<2.5)
Requires-Dist: Pillow (>=2.5,<2.6)
Requires-Dist: pyserial (>=2.7,<2.8)
Provides-Extra: dev
Requires-Dist: flake8 (>=2.2,<2.3); extra == 'dev'
Requires-Dist: mccabe (>=0.2,<0.3); extra == 'dev'
Requires-Dist: pep8 (>=1.5,<1.6); extra == 'dev'
Requires-Dist: pip-tools (>=0.3,<0.4); extra == 'dev'
Requires-Dist: pyflakes (>=0.8.1,<0.9); extra == 'dev'
Requires-Dist: wheel (>=0.24,<0.25); extra == 'dev'
